LICENSE
jars/graphframes-0.6.0-spark2.3-s_2.11.jar
jars/graphframes-0.7.0-spark2.3-s_2.11.jar
jars/graphframes-0.8.0-spark3.0-s_2.12.jar
jars/graphframes-0.8.2-spark3.1-s_2.12.jar
jars/scala-logging-api_2.11-2.1.2.jar
jars/scala-logging-slf4j_2.11-2.1.2.jar
notebooks/data/df_e.snappy.parquet
notebooks/graphframes_splink_graph_demo.ipynb
splink_graph/__init__.py
splink_graph/cc.py
splink_graph/cluster_metrics.py
splink_graph/edge_metrics.py
splink_graph/embedding/__init__.py
splink_graph/embedding/n2v.py
splink_graph/node_metrics.py
splink_graph/utils.py
splink_graph-0.8.2.dist-info/LICENSE
splink_graph-0.8.2.dist-info/WHEEL
splink_graph-0.8.2.dist-info/METADATA
splink_graph-0.8.2.dist-info/RECORD
