Metadata-Version: 2.1
Name: splink-graph
Version: 0.8.2
Summary: a small set of graph functions to be used from pySpark on top of networkx and graphframes
Home-page: https://github.com/moj-analytical-services/splink_graph
License: MIT
Keywords: graph theory,graph metrics
Author: Theodore Manassis
Author-email: theodore.manassis@digital.justice.gov.uk
Requires-Python: >=3.8
Classifier: License :: OSI Approved :: MIT License
Classifier: Programming Language :: Python :: 3
Classifier: Programming Language :: Python :: 3.8
Classifier: Programming Language :: Python :: 3.9
Classifier: Programming Language :: Python :: 3.10
Classifier: Programming Language :: Python :: 3.11
Requires-Dist: gensim (<4.1.0)
Requires-Dist: graphframes (>=0.8.2)
Requires-Dist: networkx (>=2.7.1,<2.8.0)
Requires-Dist: node2vec (==0.4.3)
Requires-Dist: numpy (>=1.20)
Requires-Dist: scipy (>=1.8)
Project-URL: Repository, https://github.com/moj-analytical-services/splink_graph
